hostedpi/__init__.py
hostedpi/auth.py
hostedpi/cli/__init__.py
hostedpi/cli/arguments.py
hostedpi/cli/format.py
hostedpi/cli/options.py
hostedpi/cli/ssh.py
hostedpi/cli/sshkeys.py
hostedpi/cli/utils.py
hostedpi/exc.py
hostedpi/logger.py
hostedpi/models/__init__.py
hostedpi/models/mythic/__init__.py
hostedpi/models/mythic/payloads.py
hostedpi/models/mythic/responses.py
hostedpi/models/specs.py
hostedpi/models/sshkeys.py
hostedpi/pi.py
hostedpi/picloud.py
hostedpi/settings.py
hostedpi/utils.py
hostedpi-0.4.6.dist-info/METADATA
hostedpi-0.4.6.dist-info/WHEEL
hostedpi-0.4.6.dist-info/entry_points.txt
hostedpi-0.4.6.dist-info/licenses/LICENSE.txt
hostedpi-0.4.6.dist-info/RECORD
