Metadata-Version: 2.4
Name: hostedpi
Version: 0.4.6
Summary: Python interface to the Mythic Beasts Hosted Pi API
License: BSD 3-Clause License
License-File: LICENSE.txt
Keywords: raspberrypi,piwheels,mythicbeasts,hostedpi,picloud
Author: Ben Nuttall
Author-email: ben@bennuttall.com
Requires-Python: >=3.9,<4.0
Classifier: Development Status :: 4 - Beta
Classifier: Programming Language :: Python :: 3
Classifier: Programming Language :: Python :: 3 :: Only
Classifier: Programming Language :: Python :: 3.9
Classifier: Programming Language :: Python :: 3.10
Classifier: Programming Language :: Python :: 3.11
Classifier: Programming Language :: Python :: 3.12
Classifier: Programming Language :: Python :: 3.13
Classifier: Programming Language :: Python :: 3.14
Classifier: Intended Audience :: Developers
Classifier: Topic :: Utilities
Provides-Extra: cli
Provides-Extra: test
Requires-Dist: pydantic (>=2,<3.0.0)
Requires-Dist: pydantic-settings (>=2.7.1,<3.0.0)
Requires-Dist: pytest (>=8.4.1,<9.0.0) ; extra == "test"
Requires-Dist: pytest-cov (>=6.2.1,<7.0.0) ; extra == "test"
Requires-Dist: requests (>=2.32.3,<3.0.0)
Requires-Dist: rich (>=13.9.4,<14.0.0) ; extra == "cli"
Requires-Dist: structlog (>=25.1.0)
Requires-Dist: typer (>=0.15.1,<1.0.0) ; extra == "cli"
Project-URL: Changelog, https://hostedpi.readthedocs.io/en/stable/changelog.html
Project-URL: Documentation, https://hostedpi.readthedocs.io
Project-URL: Issues, https://github.com/piwheels/hostedpi/issues
Project-URL: Repository, https://github.com/piwheels/hostedpi
